{
  "resourceType" : "CodeSystem",
  "id" : "9eb43b47-6129-49d2-a046-7879462fc2d2-12",
  "url" : "http://hl7.org/fhir/comparison/CodeSystem/9eb43b47-6129-49d2-a046-7879462fc2d2-12",
  "name" : "IntersectionAdministrativeGenderDkSupplementAndAdministrativeGenderDkSupplement",
  "title" : "Intersection of DK Administrative Gender Supplement And DK Administrative Gender Supplement",
  "status" : "draft",
  "date" : "2022-12-05T08:58:47+00:00",
  "jurisdiction" : [{
    "coding" : [{
      "system" : "urn:iso:std:iso:3166",
      "code" : "DK",
      "display" : "Denmark"
    }]
  }],
  "concept" : [{
    "code" : "male",
    "designation" : [{
      "language" : "da",
      "value" : "Mand"
    }]
  },
  {
    "code" : "female",
    "designation" : [{
      "language" : "da",
      "value" : "Kvinde"
    }]
  },
  {
    "code" : "other",
    "designation" : [{
      "language" : "da",
      "value" : "Andet"
    }]
  },
  {
    "code" : "unknown",
    "designation" : [{
      "language" : "da",
      "value" : "Ukendt"
    }]
  }]
}