{
  "resourceType" : "CodeSystem",
  "id" : "e56d3e56-d29d-4914-bade-1b0ae07c9060-45",
  "url" : "http://hl7.org/fhir/comparison/CodeSystem/e56d3e56-d29d-4914-bade-1b0ae07c9060-45",
  "name" : "IntersectionRequestStatusAndRequestStatus",
  "title" : "Intersection of DK Request Status And DK Request Status",
  "status" : "active",
  "date" : "2024-04-16T10:59:00+00:00",
  "jurisdiction" : [{
    "coding" : [{
      "system" : "urn:iso:std:iso:3166",
      "code" : "DK",
      "display" : "Denmark"
    }]
  }],
  "concept" : [{
    "code" : "draft",
    "designation" : [{
      "language" : "da",
      "use" : {
        "system" : "http://snomed.info/sct",
        "code" : "900000000000013009"
      },
      "value" : "Udkast"
    }]
  },
  {
    "code" : "active",
    "designation" : [{
      "language" : "da",
      "use" : {
        "system" : "http://snomed.info/sct",
        "code" : "900000000000013009"
      },
      "value" : "Aktiv"
    }]
  },
  {
    "code" : "on-hold",
    "designation" : [{
      "language" : "da",
      "use" : {
        "system" : "http://snomed.info/sct",
        "code" : "900000000000013009"
      },
      "value" : "Suspenderet"
    }]
  },
  {
    "code" : "revoked",
    "designation" : [{
      "language" : "da",
      "use" : {
        "system" : "http://snomed.info/sct",
        "code" : "900000000000013009"
      },
      "value" : "Annulleret"
    }]
  },
  {
    "code" : "completed",
    "designation" : [{
      "language" : "da",
      "use" : {
        "system" : "http://snomed.info/sct",
        "code" : "900000000000013009"
      },
      "value" : "Afsluttet"
    }]
  },
  {
    "code" : "entered-in-error",
    "designation" : [{
      "language" : "da",
      "use" : {
        "system" : "http://snomed.info/sct",
        "code" : "900000000000013009"
      },
      "value" : "Fejlindtastning"
    }]
  },
  {
    "code" : "unknown",
    "designation" : [{
      "language" : "da",
      "use" : {
        "system" : "http://snomed.info/sct",
        "code" : "900000000000013009"
      },
      "value" : "Ukendt"
    }]
  }]
}